ragents.py
recsagents23-6.2.0.dist-info/LICENSE.txt
recsagents23-6.2.0.dist-info/METADATA
recsagents23-6.2.0.dist-info/WHEEL
recsagents23-6.2.0.dist-info/top_level.txt
recsagents23-6.2.0.dist-info/RECORD
