Metadata-Version: 2.1
Name: recsagents23
Version: 6.2.0
Summary: some package
Classifier: Programming Language :: Python :: 3
Classifier: License :: OSI Approved :: MIT License
Classifier: Operating System :: OS Independent
License-File: LICENSE.txt
Requires-Dist: pandas
Requires-Dist: numpy
Requires-Dist: matplotlib
Requires-Dist: tqdm
Requires-Dist: helperagent (==4.0.0)
Requires-Dist: datetime
Requires-Dist: xgboost
Requires-Dist: statsmodels
Requires-Dist: interpret
Requires-Dist: shap
Requires-Dist: entsoe-py
Requires-Dist: beautifulsoup4 (==4.11.2)
Provides-Extra: dev
Requires-Dist: pytest ; extra == 'dev'
